easyjoblite/__init__.py
easyjoblite/cli.py
easyjoblite/configuration.py
easyjoblite/constants.py
easyjoblite/easy_api.py
easyjoblite/exception.py
easyjoblite/job.py
easyjoblite/job_response.py
easyjoblite/orchestrator.py
easyjoblite/response.py
easyjoblite/state.py
easyjoblite/utils.py
easyjoblite/version.py
easyjoblite/consumers/__init__.py
easyjoblite/consumers/base_rmq_consumer.py
easyjoblite/consumers/dead_letter_queue_consumer.py
easyjoblite/consumers/retry_queue_consumer.py
easyjoblite/consumers/work_queue_consumer.py
easyjoblite/workers/__init__.py
easyjoblite/workers/worker_manager.py
easyjoblite-0.7.6.dist-info/DESCRIPTION.rst
easyjoblite-0.7.6.dist-info/METADATA
easyjoblite-0.7.6.dist-info/RECORD
easyjoblite-0.7.6.dist-info/WHEEL
easyjoblite-0.7.6.dist-info/entry_points.txt
easyjoblite-0.7.6.dist-info/metadata.json
easyjoblite-0.7.6.dist-info/top_level.txt
