Metadata-Version: 2.0
Name: easyjoblite
Version: 0.7.6
Summary: A lite weight job scheduler which supports both automated and manual retry.
Home-page: UNKNOWN
Author: bkp
Author-email: bibek.padhy@treebohotels.com
License: BSD
Platform: UNKNOWN
Requires-Dist: PyYaml
Requires-Dist: click (>=3.0.0)
Requires-Dist: kombu (==3.0.35)
